binary_protocol/__init__.py
binary_protocol/benchmark/__init__.py
binary_protocol/benchmark/base.py
binary_protocol/benchmark/implementations.py
binary_protocol/benchmark/orchestrator.py
binary_protocol/benchmark/reporter.py
binary_protocol/benchmark/runner.py
binary_protocol/client/__init__.py
binary_protocol/client/client.py
binary_protocol/protocol/__init__.py
binary_protocol/protocol/config.py
binary_protocol/protocol/constants.py
binary_protocol/protocol/exceptions.py
binary_protocol/protocol/message_structure.py
binary_protocol/protocol/messages.py
binary_protocol/server/__init__.py
binary_protocol/server/server.py
binary_protocol-0.2.2.dist-info/LICENSE
binary_protocol-0.2.2.dist-info/METADATA
binary_protocol-0.2.2.dist-info/WHEEL
binary_protocol-0.2.2.dist-info/top_level.txt
binary_protocol-0.2.2.dist-info/RECORD
