Metadata-Version: 2.1
Name: binary-protocol
Version: 0.2.2
Summary: A lightweight binary protocol implementation
Author: Blaz Aristovnik
Project-URL: Homepage, https://github.com/barisgit/binary-protocol
Classifier: Development Status :: 3 - Alpha
Classifier: Programming Language :: Python :: 3.8
Classifier: Programming Language :: Python :: 3.9
Classifier: Programming Language :: Python :: 3.10
Requires-Python: >=3.8
License-File: LICENSE
